[
    {"reading":"Genesis 1", "date":"2022-09-05T09:00:00.000Z"},
    {"reading":"Genesis 2", "date":"2022-09-06T09:00:00.000Z"},
    {"reading":"Genesis 3", "date":"2022-09-07T09:00:00.000Z"},
    {"reading":"Genesis 4", "date":"2022-09-08T09:00:00.000Z"},
    {"reading":"Genesis 5", "date":"2022-09-09T09:00:00.000Z"},
    {"reading":"Genesis 6", "date":"2022-09-10T09:00:00.000Z"},
    {"reading":"Genesis 7", "date":"2022-09-11T09:00:00.000Z"},
    {"reading":"Genesis 8", "date":"2022-09-12T09:00:00.000Z"},
    {"reading":"Genesis 9", "date":"2022-09-13T09:00:00.000Z"},
    {"reading":"Genesis 10", "date":"2022-09-14T09:00:00.000Z"},
    {"reading":"Genesis 11", "date":"2022-09-15T09:00:00.000Z"},
    {"reading":"Genesis 12", "date":"2022-09-16T09:00:00.000Z"},
    {"reading":"Genesis 13", "date":"2022-09-17T09:00:00.000Z"},
    {"reading":"Genesis 14", "date":"2022-09-18T09:00:00.000Z"},
    {"reading":"Genesis 15", "date":"2022-09-19T09:00:00.000Z"},
    {"reading":"Genesis 16", "date":"2022-09-20T09:00:00.000Z"},
    {"reading":"Genesis 17", "date":"2022-09-21T09:00:00.000Z"},
    {"reading":"Genesis 18", "date":"2022-09-22T09:00:00.000Z"},
    {"reading":"Genesis 19", "date":"2022-09-23T09:00:00.000Z"},
    {"reading":"Genesis 20", "date":"2022-09-24T09:00:00.000Z"},
    {"reading":"Genesis 21", "date":"2022-09-25T09:00:00.000Z"},
    {"reading":"Genesis 22", "date":"2022-09-26T09:00:00.000Z"},
    {"reading":"Genesis 23", "date":"2022-09-27T09:00:00.000Z"},
    {"reading":"Genesis 24", "date":"2022-09-28T09:00:00.000Z"},
    {"reading":"Genesis 25", "date":"2022-09-29T09:00:00.000Z"},
    {"reading":"Genesis 26", "date":"2022-09-30T09:00:00.000Z"},
    {"reading":"Genesis 27", "date":"2022-10-01T09:00:00.000Z"},
    {"reading":"Genesis 28", "date":"2022-10-02T09:00:00.000Z"},
    {"reading":"Genesis 29", "date":"2022-10-03T09:00:00.000Z"},
    {"reading":"Genesis 30", "date":"2022-10-04T09:00:00.000Z"},
    {"reading":"Genesis 31", "date":"2022-10-05T09:00:00.000Z"},
    {"reading":"Genesis 32", "date":"2022-10-06T09:00:00.000Z"},
    {"reading":"Genesis 33", "date":"2022-10-07T09:00:00.000Z"},
    {"reading":"Genesis 34", "date":"2022-10-08T09:00:00.000Z"},
    {"reading":"Genesis 35", "date":"2022-10-09T09:00:00.000Z"},
    {"reading":"Genesis 36", "date":"2022-10-10T09:00:00.000Z"},
    {"reading":"Genesis 37", "date":"2022-10-11T09:00:00.000Z"},
    {"reading":"Genesis 38", "date":"2022-10-12T09:00:00.000Z"},
    {"reading":"Genesis 39", "date":"2022-10-13T09:00:00.000Z"},
    {"reading":"Genesis 40", "date":"2022-10-14T09:00:00.000Z"},
    {"reading":"Genesis 41", "date":"2022-10-15T09:00:00.000Z"},
    {"reading":"Genesis 42", "date":"2022-10-16T09:00:00.000Z"},
    {"reading":"Genesis 43", "date":"2022-10-17T09:00:00.000Z"},
    {"reading":"Genesis 44", "date":"2022-10-18T09:00:00.000Z"},
    {"reading":"Genesis 45", "date":"2022-10-19T09:00:00.000Z"},
    {"reading":"Genesis 46", "date":"2022-10-20T09:00:00.000Z"},
    {"reading":"Genesis 47", "date":"2022-10-21T09:00:00.000Z"},
    {"reading":"Genesis 48", "date":"2022-10-22T09:00:00.000Z"},
    {"reading":"Genesis 49", "date":"2022-10-23T09:00:00.000Z"},
    {"reading":"Genesis 50", "date":"2022-10-24T09:00:00.000Z"},
    {"reading":"Exodus 1", "date":"2022-10-25T09:00:00.000Z"},
    {"reading":"Exodus 2", "date":"2022-10-26T09:00:00.000Z"},
    {"reading":"Exodus 3", "date":"2022-10-27T09:00:00.000Z"},
    {"reading":"Exodus 4", "date":"2022-10-28T09:00:00.000Z"},
    {"reading":"Exodus 5", "date":"2022-10-29T09:00:00.000Z"},
    {"reading":"Exodus 6", "date":"2022-10-30T09:00:00.000Z"},
    {"reading":"Exodus 7", "date":"2022-10-31T09:00:00.000Z"},
    {"reading":"Exodus 8", "date":"2022-11-01T09:00:00.000Z"},
    {"reading":"Exodus 9", "date":"2022-11-02T09:00:00.000Z"},
    {"reading":"Exodus 10", "date":"2022-11-03T09:00:00.000Z"},
    {"reading":"Exodus 11", "date":"2022-11-04T09:00:00.000Z"},
    {"reading":"Exodus 12", "date":"2022-11-05T09:00:00.000Z"},
    {"reading":"Exodus 13", "date":"2022-11-06T09:00:00.000Z"},
    {"reading":"Exodus 14", "date":"2022-11-07T09:00:00.000Z"},
    {"reading":"Exodus 15", "date":"2022-11-08T09:00:00.000Z"},
    {"reading":"Exodus 16", "date":"2022-11-09T09:00:00.000Z"},
    {"reading":"Exodus 17", "date":"2022-11-10T09:00:00.000Z"},
    {"reading":"Exodus 18", "date":"2022-11-11T09:00:00.000Z"},
    {"reading":"Exodus 19", "date":"2022-11-12T09:00:00.000Z"},
    {"reading":"Exodus 20", "date":"2022-11-13T09:00:00.000Z"},
    {"reading":"Exodus 21", "date":"2022-11-14T09:00:00.000Z"},
    {"reading":"Exodus 22", "date":"2022-11-15T09:00:00.000Z"},
    {"reading":"Exodus 23", "date":"2022-11-16T09:00:00.000Z"},
    {"reading":"Exodus 24", "date":"2022-11-17T09:00:00.000Z"},
    {"reading":"Exodus 25", "date":"2022-11-18T09:00:00.000Z"},
    {"reading":"Exodus 26", "date":"2022-11-19T09:00:00.000Z"},
    {"reading":"Exodus 27", "date":"2022-11-20T09:00:00.000Z"},
    {"reading":"Exodus 28", "date":"2022-11-21T09:00:00.000Z"},
    {"reading":"Exodus 29", "date":"2022-11-22T09:00:00.000Z"},
    {"reading":"Exodus 30", "date":"2022-11-23T09:00:00.000Z"},
    {"reading":"Exodus 31", "date":"2022-11-24T09:00:00.000Z"},
    {"reading":"Exodus 32", "date":"2022-11-25T09:00:00.000Z"},
    {"reading":"Exodus 33", "date":"2022-11-26T09:00:00.000Z"},
    {"reading":"Exodus 34", "date":"2022-11-27T09:00:00.000Z"},
    {"reading":"Exodus 35", "date":"2022-11-28T09:00:00.000Z"},
    {"reading":"Exodus 36", "date":"2022-11-29T09:00:00.000Z"},
    {"reading":"Exodus 37", "date":"2022-11-30T09:00:00.000Z"},
    {"reading":"Exodus 38", "date":"2022-12-01T09:00:00.000Z"},
    {"reading":"Exodus 39", "date":"2022-12-02T09:00:00.000Z"},
    {"reading":"Exodus 40", "date":"2022-12-03T09:00:00.000Z"},
    {"reading":"Leviticus 1", "date":"2022-12-04T09:00:00.000Z"},
    {"reading":"Leviticus 2", "date":"2022-12-05T09:00:00.000Z"},
    {"reading":"Leviticus 3", "date":"2022-12-06T09:00:00.000Z"},
    {"reading":"Leviticus 4", "date":"2022-12-07T09:00:00.000Z"},
    {"reading":"Leviticus 5", "date":"2022-12-08T09:00:00.000Z"},
    {"reading":"Leviticus 6", "date":"2022-12-09T09:00:00.000Z"},
    {"reading":"Leviticus 7", "date":"2022-12-10T09:00:00.000Z"},
    {"reading":"Leviticus 8", "date":"2022-12-11T09:00:00.000Z"},
    {"reading":"Leviticus 9", "date":"2022-12-12T09:00:00.000Z"},
    {"reading":"Leviticus 10", "date":"2022-12-13T09:00:00.000Z"},
    {"reading":"Leviticus 11", "date":"2022-12-14T09:00:00.000Z"},
    {"reading":"Leviticus 12", "date":"2022-12-15T09:00:00.000Z"},
    {"reading":"Leviticus 13", "date":"2022-12-16T09:00:00.000Z"},
    {"reading":"Leviticus 14", "date":"2022-12-17T09:00:00.000Z"},
    {"reading":"Leviticus 15", "date":"2022-12-18T09:00:00.000Z"},
    {"reading":"Leviticus 16", "date":"2022-12-19T09:00:00.000Z"},
    {"reading":"Leviticus 17", "date":"2022-12-20T09:00:00.000Z"},
    {"reading":"Leviticus 18", "date":"2022-12-21T09:00:00.000Z"},
    {"reading":"Leviticus 19", "date":"2022-12-22T09:00:00.000Z"},
    {"reading":"Leviticus 20", "date":"2022-12-23T09:00:00.000Z"},
    {"reading":"Leviticus 21", "date":"2022-12-24T09:00:00.000Z"},
    {"reading":"Leviticus 22", "date":"2022-12-25T09:00:00.000Z"},
    {"reading":"Leviticus 23", "date":"2022-12-26T09:00:00.000Z"},
    {"reading":"Leviticus 24", "date":"2022-12-27T09:00:00.000Z"},
    {"reading":"Leviticus 25", "date":"2022-12-28T09:00:00.000Z"},
    {"reading":"Leviticus 26", "date":"2022-12-29T09:00:00.000Z"},
    {"reading":"Leviticus 27", "date":"2022-12-30T09:00:00.000Z"},
    {"reading":"Numbers 1", "date":"2022-12-31T09:00:00.000Z"},
    {"reading":"Numbers 2", "date":"2023-01-01T09:00:00.000Z"},
    {"reading":"Numbers 3", "date":"2023-01-02T09:00:00.000Z"},
    {"reading":"Numbers 4", "date":"2023-01-03T09:00:00.000Z"},
    {"reading":"Numbers 5", "date":"2023-01-04T09:00:00.000Z"},
    {"reading":"Numbers 6", "date":"2023-01-05T09:00:00.000Z"},
    {"reading":"Numbers 7", "date":"2023-01-06T09:00:00.000Z"},
    {"reading":"Numbers 8", "date":"2023-01-07T09:00:00.000Z"},
    {"reading":"Numbers 9", "date":"2023-01-08T09:00:00.000Z"},
    {"reading":"Numbers 10", "date":"2023-01-09T09:00:00.000Z"},
    {"reading":"Numbers 11", "date":"2023-01-10T09:00:00.000Z"},
    {"reading":"Numbers 12", "date":"2023-01-11T09:00:00.000Z"},
    {"reading":"Numbers 13", "date":"2023-01-12T09:00:00.000Z"},
    {"reading":"Numbers 14", "date":"2023-01-13T09:00:00.000Z"},
    {"reading":"Numbers 15", "date":"2023-01-14T09:00:00.000Z"},
    {"reading":"Numbers 16", "date":"2023-01-15T09:00:00.000Z"},
    {"reading":"Numbers 17", "date":"2023-01-16T09:00:00.000Z"},
    {"reading":"Numbers 18", "date":"2023-01-17T09:00:00.000Z"},
    {"reading":"Numbers 19", "date":"2023-01-18T09:00:00.000Z"},
    {"reading":"Numbers 20", "date":"2023-01-19T09:00:00.000Z"},
    {"reading":"Numbers 21", "date":"2023-01-20T09:00:00.000Z"},
    {"reading":"Numbers 22", "date":"2023-01-21T09:00:00.000Z"},
    {"reading":"Numbers 23", "date":"2023-01-22T09:00:00.000Z"},
    {"reading":"Numbers 24", "date":"2023-01-23T09:00:00.000Z"},
    {"reading":"Numbers 25", "date":"2023-01-24T09:00:00.000Z"},
    {"reading":"Numbers 26", "date":"2023-01-25T09:00:00.000Z"},
    {"reading":"Numbers 27", "date":"2023-01-26T09:00:00.000Z"},
    {"reading":"Numbers 28", "date":"2023-01-27T09:00:00.000Z"},
    {"reading":"Numbers 29", "date":"2023-01-28T09:00:00.000Z"},
    {"reading":"Numbers 30", "date":"2023-01-29T09:00:00.000Z"},
    {"reading":"Numbers 31", "date":"2023-01-30T09:00:00.000Z"},
    {"reading":"Numbers 32", "date":"2023-01-31T09:00:00.000Z"},
    {"reading":"Numbers 33", "date":"2023-02-01T09:00:00.000Z"},
    {"reading":"Numbers 34", "date":"2023-02-02T09:00:00.000Z"},
    {"reading":"Numbers 35", "date":"2023-02-03T09:00:00.000Z"},
    {"reading":"Numbers 36", "date":"2023-02-04T09:00:00.000Z"},
    {"reading":"Deuteronomy 1", "date":"2023-02-05T09:00:00.000Z"},
    {"reading":"Deuteronomy 2", "date":"2023-02-06T09:00:00.000Z"},
    {"reading":"Deuteronomy 3", "date":"2023-02-07T09:00:00.000Z"},
    {"reading":"Deuteronomy 4", "date":"2023-02-08T09:00:00.000Z"},
    {"reading":"Deuteronomy 5", "date":"2023-02-09T09:00:00.000Z"},
    {"reading":"Deuteronomy 6", "date":"2023-02-10T09:00:00.000Z"},
    {"reading":"Deuteronomy 7", "date":"2023-02-11T09:00:00.000Z"},
    {"reading":"Deuteronomy 8", "date":"2023-02-12T09:00:00.000Z"},
    {"reading":"Deuteronomy 9", "date":"2023-02-13T09:00:00.000Z"},
    {"reading":"Deuteronomy 10", "date":"2023-02-14T09:00:00.000Z"},
    {"reading":"Deuteronomy 11", "date":"2023-02-15T09:00:00.000Z"},
    {"reading":"Deuteronomy 12", "date":"2023-02-16T09:00:00.000Z"},
    {"reading":"Deuteronomy 13", "date":"2023-02-17T09:00:00.000Z"},
    {"reading":"Deuteronomy 14", "date":"2023-02-18T09:00:00.000Z"},
    {"reading":"Deuteronomy 15", "date":"2023-02-19T09:00:00.000Z"},
    {"reading":"Deuteronomy 16", "date":"2023-02-20T09:00:00.000Z"},
    {"reading":"Deuteronomy 17", "date":"2023-02-21T09:00:00.000Z"},
    {"reading":"Deuteronomy 18", "date":"2023-02-22T09:00:00.000Z"},
    {"reading":"Deuteronomy 19", "date":"2023-02-23T09:00:00.000Z"},
    {"reading":"Deuteronomy 20", "date":"2023-02-24T09:00:00.000Z"},
    {"reading":"Deuteronomy 21", "date":"2023-02-25T09:00:00.000Z"},
    {"reading":"Deuteronomy 22", "date":"2023-02-26T09:00:00.000Z"},
    {"reading":"Deuteronomy 23", "date":"2023-02-27T09:00:00.000Z"},
    {"reading":"Deuteronomy 24", "date":"2023-02-28T09:00:00.000Z"},
    {"reading":"Deuteronomy 25", "date":"2023-03-01T09:00:00.000Z"},
    {"reading":"Deuteronomy 26", "date":"2023-03-02T09:00:00.000Z"},
    {"reading":"Deuteronomy 27", "date":"2023-03-03T09:00:00.000Z"},
    {"reading":"Deuteronomy 28", "date":"2023-03-04T09:00:00.000Z"},
    {"reading":"Deuteronomy 29", "date":"2023-03-05T09:00:00.000Z"},
    {"reading":"Deuteronomy 30", "date":"2023-03-06T09:00:00.000Z"},
    {"reading":"Deuteronomy 31", "date":"2023-03-07T09:00:00.000Z"},
    {"reading":"Deuteronomy 32", "date":"2023-03-08T09:00:00.000Z"},
    {"reading":"Deuteronomy 33", "date":"2023-03-09T09:00:00.000Z"},
    {"reading":"Deuteronomy 34", "date":"2023-03-10T09:00:00.000Z"},
    {"reading":"Joshua 1", "date":"2023-03-11T09:00:00.000Z"},
    {"reading":"Joshua 2", "date":"2023-03-12T09:00:00.000Z"},
    {"reading":"Joshua 3", "date":"2023-03-13T09:00:00.000Z"},
    {"reading":"Joshua 4", "date":"2023-03-14T09:00:00.000Z"},
    {"reading":"Joshua 5", "date":"2023-03-15T09:00:00.000Z"},
    {"reading":"Joshua 6", "date":"2023-03-16T09:00:00.000Z"},
    {"reading":"Joshua 7", "date":"2023-03-17T09:00:00.000Z"},
    {"reading":"Joshua 8", "date":"2023-03-18T09:00:00.000Z"},
    {"reading":"Joshua 9", "date":"2023-03-19T09:00:00.000Z"},
    {"reading":"Joshua 10", "date":"2023-03-20T09:00:00.000Z"},
    {"reading":"Joshua 11", "date":"2023-03-21T09:00:00.000Z"},
    {"reading":"Joshua 12", "date":"2023-03-22T09:00:00.000Z"},
    {"reading":"Joshua 13", "date":"2023-03-23T09:00:00.000Z"},
    {"reading":"Joshua 14", "date":"2023-03-24T09:00:00.000Z"},
    {"reading":"Joshua 15", "date":"2023-03-25T09:00:00.000Z"},
    {"reading":"Joshua 16", "date":"2023-03-26T09:00:00.000Z"},
    {"reading":"Joshua 17", "date":"2023-03-27T09:00:00.000Z"},
    {"reading":"Joshua 18", "date":"2023-03-28T09:00:00.000Z"},
    {"reading":"Joshua 19", "date":"2023-03-29T09:00:00.000Z"},
    {"reading":"Joshua 20", "date":"2023-03-30T09:00:00.000Z"},
    {"reading":"Joshua 21", "date":"2023-03-31T09:00:00.000Z"},
    {"reading":"Joshua 22", "date":"2023-04-01T09:00:00.000Z"},
    {"reading":"Joshua 23", "date":"2023-04-02T09:00:00.000Z"},
    {"reading":"Joshua 24", "date":"2023-04-03T09:00:00.000Z"},
    {"reading":"Judges 1", "date":"2023-04-04T09:00:00.000Z"},
    {"reading":"Judges 2", "date":"2023-04-05T09:00:00.000Z"},
    {"reading":"Judges 3", "date":"2023-04-06T09:00:00.000Z"},
    {"reading":"Judges 4", "date":"2023-04-07T09:00:00.000Z"},
    {"reading":"Judges 5", "date":"2023-04-08T09:00:00.000Z"},
    {"reading":"Judges 6", "date":"2023-04-09T09:00:00.000Z"},
    {"reading":"Judges 7", "date":"2023-04-10T09:00:00.000Z"},
    {"reading":"Judges 8", "date":"2023-04-11T09:00:00.000Z"},
    {"reading":"Judges 9", "date":"2023-04-12T09:00:00.000Z"},
    {"reading":"Judges 10", "date":"2023-04-13T09:00:00.000Z"},
    {"reading":"Judges 11", "date":"2023-04-14T09:00:00.000Z"},
    {"reading":"Judges 12", "date":"2023-04-15T09:00:00.000Z"},
    {"reading":"Judges 13", "date":"2023-04-16T09:00:00.000Z"},
    {"reading":"Judges 14", "date":"2023-04-17T09:00:00.000Z"},
    {"reading":"Judges 15", "date":"2023-04-18T09:00:00.000Z"},
    {"reading":"Judges 16", "date":"2023-04-19T09:00:00.000Z"},
    {"reading":"Judges 17", "date":"2023-04-20T09:00:00.000Z"},
    {"reading":"Judges 18", "date":"2023-04-21T09:00:00.000Z"},
    {"reading":"Judges 19", "date":"2023-04-22T09:00:00.000Z"},
    {"reading":"Judges 20", "date":"2023-04-23T09:00:00.000Z"},
    {"reading":"Judges 21", "date":"2023-04-24T09:00:00.000Z"},
    {"reading":"Ruth 1", "date":"2023-04-25T09:00:00.000Z"},
    {"reading":"Ruth 2", "date":"2023-04-26T09:00:00.000Z"},
    {"reading":"Ruth 3", "date":"2023-04-27T09:00:00.000Z"},
    {"reading":"Ruth 4", "date":"2023-04-28T09:00:00.000Z"},
    {"reading":"1 Samuel 1", "date":"2023-04-29T09:00:00.000Z"},
    {"reading":"1 Samuel 2", "date":"2023-04-30T09:00:00.000Z"},
    {"reading":"1 Samuel 3", "date":"2023-05-01T09:00:00.000Z"},
    {"reading":"1 Samuel 4", "date":"2023-05-02T09:00:00.000Z"},
    {"reading":"1 Samuel 5", "date":"2023-05-03T09:00:00.000Z"},
    {"reading":"1 Samuel 6", "date":"2023-05-04T09:00:00.000Z"},
    {"reading":"1 Samuel 7", "date":"2023-05-05T09:00:00.000Z"},
    {"reading":"1 Samuel 8", "date":"2023-05-06T09:00:00.000Z"},
    {"reading":"1 Samuel 9", "date":"2023-05-07T09:00:00.000Z"},
    {"reading":"1 Samuel 10", "date":"2023-05-08T09:00:00.000Z"},
    {"reading":"1 Samuel 11", "date":"2023-05-09T09:00:00.000Z"},
    {"reading":"1 Samuel 12", "date":"2023-05-10T09:00:00.000Z"},
    {"reading":"1 Samuel 13", "date":"2023-05-11T09:00:00.000Z"},
    {"reading":"1 Samuel 14", "date":"2023-05-12T09:00:00.000Z"},
    {"reading":"1 Samuel 15", "date":"2023-05-13T09:00:00.000Z"},
    {"reading":"1 Samuel 16", "date":"2023-05-14T09:00:00.000Z"},
    {"reading":"1 Samuel 17", "date":"2023-05-15T09:00:00.000Z"},
    {"reading":"1 Samuel 18", "date":"2023-05-16T09:00:00.000Z"},
    {"reading":"1 Samuel 19", "date":"2023-05-17T09:00:00.000Z"},
    {"reading":"1 Samuel 20", "date":"2023-05-18T09:00:00.000Z"},
    {"reading":"1 Samuel 21", "date":"2023-05-19T09:00:00.000Z"},
    {"reading":"1 Samuel 22", "date":"2023-05-20T09:00:00.000Z"},
    {"reading":"1 Samuel 23", "date":"2023-05-21T09:00:00.000Z"},
    {"reading":"1 Samuel 24", "date":"2023-05-22T09:00:00.000Z"},
    {"reading":"1 Samuel 25", "date":"2023-05-23T09:00:00.000Z"},
    {"reading":"1 Samuel 26", "date":"2023-05-24T09:00:00.000Z"},
    {"reading":"1 Samuel 27", "date":"2023-05-25T09:00:00.000Z"},
    {"reading":"1 Samuel 28", "date":"2023-05-26T09:00:00.000Z"},
    {"reading":"1 Samuel 29", "date":"2023-05-27T09:00:00.000Z"},
    {"reading":"1 Samuel 30", "date":"2023-05-28T09:00:00.000Z"},
    {"reading":"1 Samuel 31", "date":"2023-05-29T09:00:00.000Z"},
    {"reading":"2 Samuel 1", "date":"2023-05-30T09:00:00.000Z"},
    {"reading":"2 Samuel 2", "date":"2023-05-31T09:00:00.000Z"},
    {"reading":"2 Samuel 3", "date":"2023-06-01T09:00:00.000Z"},
    {"reading":"2 Samuel 4", "date":"2023-06-02T09:00:00.000Z"},
    {"reading":"2 Samuel 5", "date":"2023-06-03T09:00:00.000Z"},
    {"reading":"2 Samuel 6", "date":"2023-06-04T09:00:00.000Z"},
    {"reading":"2 Samuel 7", "date":"2023-06-05T09:00:00.000Z"},
    {"reading":"2 Samuel 8", "date":"2023-06-06T09:00:00.000Z"},
    {"reading":"2 Samuel 9", "date":"2023-06-07T09:00:00.000Z"},
    {"reading":"2 Samuel 10", "date":"2023-06-08T09:00:00.000Z"},
    {"reading":"2 Samuel 11", "date":"2023-06-09T09:00:00.000Z"},
    {"reading":"2 Samuel 12", "date":"2023-06-10T09:00:00.000Z"},
    {"reading":"2 Samuel 13", "date":"2023-06-11T09:00:00.000Z"},
    {"reading":"2 Samuel 14", "date":"2023-06-12T09:00:00.000Z"},
    {"reading":"2 Samuel 15", "date":"2023-06-13T09:00:00.000Z"},
    {"reading":"2 Samuel 16", "date":"2023-06-14T09:00:00.000Z"},
    {"reading":"2 Samuel 17", "date":"2023-06-15T09:00:00.000Z"},
    {"reading":"2 Samuel 18", "date":"2023-06-16T09:00:00.000Z"},
    {"reading":"2 Samuel 19", "date":"2023-06-17T09:00:00.000Z"},
    {"reading":"2 Samuel 20", "date":"2023-06-18T09:00:00.000Z"},
    {"reading":"2 Samuel 21", "date":"2023-06-19T09:00:00.000Z"},
    {"reading":"2 Samuel 22", "date":"2023-06-20T09:00:00.000Z"},
    {"reading":"2 Samuel 23", "date":"2023-06-21T09:00:00.000Z"},
    {"reading":"2 Samuel 24", "date":"2023-06-22T09:00:00.000Z"},
    {"reading":"1 Kings 1", "date":"2023-06-23T09:00:00.000Z"},
    {"reading":"1 Kings 2", "date":"2023-06-24T09:00:00.000Z"},
    {"reading":"1 Kings 3", "date":"2023-06-25T09:00:00.000Z"},
    {"reading":"1 Kings 4", "date":"2023-06-26T09:00:00.000Z"},
    {"reading":"1 Kings 5", "date":"2023-06-27T09:00:00.000Z"},
    {"reading":"1 Kings 6", "date":"2023-06-28T09:00:00.000Z"},
    {"reading":"1 Kings 7", "date":"2023-06-29T09:00:00.000Z"},
    {"reading":"1 Kings 8", "date":"2023-06-30T09:00:00.000Z"},
    {"reading":"1 Kings 9", "date":"2023-07-01T09:00:00.000Z"},
    {"reading":"1 Kings 10", "date":"2023-07-02T09:00:00.000Z"},
    {"reading":"1 Kings 11", "date":"2023-07-03T09:00:00.000Z"},
    {"reading":"1 Kings 12", "date":"2023-07-04T09:00:00.000Z"},
    {"reading":"1 Kings 13", "date":"2023-07-05T09:00:00.000Z"},
    {"reading":"1 Kings 14", "date":"2023-07-06T09:00:00.000Z"},
    {"reading":"1 Kings 15", "date":"2023-07-07T09:00:00.000Z"},
    {"reading":"1 Kings 16", "date":"2023-07-08T09:00:00.000Z"},
    {"reading":"1 Kings 17", "date":"2023-07-09T09:00:00.000Z"},
    {"reading":"1 Kings 18", "date":"2023-07-10T09:00:00.000Z"},
    {"reading":"1 Kings 19", "date":"2023-07-11T09:00:00.000Z"},
    {"reading":"1 Kings 20", "date":"2023-07-12T09:00:00.000Z"},
    {"reading":"1 Kings 21", "date":"2023-07-13T09:00:00.000Z"},
    {"reading":"1 Kings 22", "date":"2023-07-14T09:00:00.000Z"},
    {"reading":"2 Kings 1", "date":"2023-07-15T09:00:00.000Z"},
    {"reading":"2 Kings 2", "date":"2023-07-16T09:00:00.000Z"},
    {"reading":"2 Kings 3", "date":"2023-07-17T09:00:00.000Z"},
    {"reading":"2 Kings 4", "date":"2023-07-18T09:00:00.000Z"},
    {"reading":"2 Kings 5", "date":"2023-07-19T09:00:00.000Z"},
    {"reading":"2 Kings 6", "date":"2023-07-20T09:00:00.000Z"},
    {"reading":"2 Kings 7", "date":"2023-07-21T09:00:00.000Z"},
    {"reading":"2 Kings 8", "date":"2023-07-22T09:00:00.000Z"},
    {"reading":"2 Kings 9", "date":"2023-07-23T09:00:00.000Z"},
    {"reading":"2 Kings 10", "date":"2023-07-24T09:00:00.000Z"},
    {"reading":"2 Kings 11", "date":"2023-07-25T09:00:00.000Z"},
    {"reading":"2 Kings 12", "date":"2023-07-26T09:00:00.000Z"},
    {"reading":"2 Kings 13", "date":"2023-07-27T09:00:00.000Z"},
    {"reading":"2 Kings 14", "date":"2023-07-28T09:00:00.000Z"},
    {"reading":"2 Kings 15", "date":"2023-07-29T09:00:00.000Z"},
    {"reading":"2 Kings 16", "date":"2023-07-30T09:00:00.000Z"},
    {"reading":"2 Kings 17", "date":"2023-07-31T09:00:00.000Z"},
    {"reading":"2 Kings 18", "date":"2023-08-01T09:00:00.000Z"},
    {"reading":"2 Kings 19", "date":"2023-08-02T09:00:00.000Z"},
    {"reading":"2 Kings 20", "date":"2023-08-03T09:00:00.000Z"},
    {"reading":"2 Kings 21", "date":"2023-08-04T09:00:00.000Z"},
    {"reading":"2 Kings 22", "date":"2023-08-05T09:00:00.000Z"},
    {"reading":"2 Kings 23", "date":"2023-08-06T09:00:00.000Z"},
    {"reading":"2 Kings 24", "date":"2023-08-07T09:00:00.000Z"},
    {"reading":"2 Kings 25", "date":"2023-08-08T09:00:00.000Z"},
    {"reading":"1 Chronicles 1", "date":"2023-08-09T09:00:00.000Z"},
    {"reading":"1 Chronicles 2", "date":"2023-08-10T09:00:00.000Z"},
    {"reading":"1 Chronicles 3", "date":"2023-08-11T09:00:00.000Z"},
    {"reading":"1 Chronicles 4", "date":"2023-08-12T09:00:00.000Z"},
    {"reading":"1 Chronicles 5", "date":"2023-08-13T09:00:00.000Z"},
    {"reading":"1 Chronicles 6", "date":"2023-08-14T09:00:00.000Z"},
    {"reading":"1 Chronicles 7", "date":"2023-08-15T09:00:00.000Z"},
    {"reading":"1 Chronicles 8", "date":"2023-08-16T09:00:00.000Z"},
    {"reading":"1 Chronicles 9", "date":"2023-08-17T09:00:00.000Z"},
    {"reading":"1 Chronicles 10", "date":"2023-08-18T09:00:00.000Z"},
    {"reading":"1 Chronicles 11", "date":"2023-08-19T09:00:00.000Z"},
    {"reading":"1 Chronicles 12", "date":"2023-08-20T09:00:00.000Z"},
    {"reading":"1 Chronicles 13", "date":"2023-08-21T09:00:00.000Z"},
    {"reading":"1 Chronicles 14", "date":"2023-08-22T09:00:00.000Z"},
    {"reading":"1 Chronicles 15", "date":"2023-08-23T09:00:00.000Z"},
    {"reading":"1 Chronicles 16", "date":"2023-08-24T09:00:00.000Z"},
    {"reading":"1 Chronicles 17", "date":"2023-08-25T09:00:00.000Z"},
    {"reading":"1 Chronicles 18", "date":"2023-08-26T09:00:00.000Z"},
    {"reading":"1 Chronicles 19", "date":"2023-08-27T09:00:00.000Z"},
    {"reading":"1 Chronicles 20", "date":"2023-08-28T09:00:00.000Z"},
    {"reading":"1 Chronicles 21", "date":"2023-08-29T09:00:00.000Z"},
    {"reading":"1 Chronicles 22", "date":"2023-08-30T09:00:00.000Z"},
    {"reading":"1 Chronicles 23", "date":"2023-08-31T09:00:00.000Z"},
    {"reading":"1 Chronicles 24", "date":"2023-09-01T09:00:00.000Z"},
    {"reading":"1 Chronicles 25", "date":"2023-09-02T09:00:00.000Z"},
    {"reading":"1 Chronicles 26", "date":"2023-09-03T09:00:00.000Z"},
    {"reading":"1 Chronicles 27", "date":"2023-09-04T09:00:00.000Z"},
    {"reading":"1 Chronicles 28", "date":"2023-09-05T09:00:00.000Z"},
    {"reading":"1 Chronicles 29", "date":"2023-09-06T09:00:00.000Z"},
    {"reading":"2 Chronicles 1", "date":"2023-09-07T09:00:00.000Z"},
    {"reading":"2 Chronicles 2", "date":"2023-09-08T09:00:00.000Z"},
    {"reading":"2 Chronicles 3", "date":"2023-09-09T09:00:00.000Z"},
    {"reading":"2 Chronicles 4", "date":"2023-09-10T09:00:00.000Z"},
    {"reading":"2 Chronicles 5", "date":"2023-09-11T09:00:00.000Z"},
    {"reading":"2 Chronicles 6", "date":"2023-09-12T09:00:00.000Z"},
    {"reading":"2 Chronicles 7", "date":"2023-09-13T09:00:00.000Z"},
    {"reading":"2 Chronicles 8", "date":"2023-09-14T09:00:00.000Z"},
    {"reading":"2 Chronicles 9", "date":"2023-09-15T09:00:00.000Z"},
    {"reading":"2 Chronicles 10", "date":"2023-09-16T09:00:00.000Z"},
    {"reading":"2 Chronicles 11", "date":"2023-09-17T09:00:00.000Z"},
    {"reading":"2 Chronicles 12", "date":"2023-09-18T09:00:00.000Z"},
    {"reading":"2 Chronicles 13", "date":"2023-09-19T09:00:00.000Z"},
    {"reading":"2 Chronicles 14", "date":"2023-09-20T09:00:00.000Z"},
    {"reading":"2 Chronicles 15", "date":"2023-09-21T09:00:00.000Z"},
    {"reading":"2 Chronicles 16", "date":"2023-09-22T09:00:00.000Z"},
    {"reading":"2 Chronicles 17", "date":"2023-09-23T09:00:00.000Z"},
    {"reading":"2 Chronicles 18", "date":"2023-09-24T09:00:00.000Z"},
    {"reading":"2 Chronicles 19", "date":"2023-09-25T09:00:00.000Z"},
    {"reading":"2 Chronicles 20", "date":"2023-09-26T09:00:00.000Z"},
    {"reading":"2 Chronicles 21", "date":"2023-09-27T09:00:00.000Z"},
    {"reading":"2 Chronicles 22", "date":"2023-09-28T09:00:00.000Z"},
    {"reading":"2 Chronicles 23", "date":"2023-09-29T09:00:00.000Z"},
    {"reading":"2 Chronicles 24", "date":"2023-09-30T09:00:00.000Z"},
    {"reading":"2 Chronicles 25", "date":"2023-10-01T09:00:00.000Z"},
    {"reading":"2 Chronicles 26", "date":"2023-10-02T09:00:00.000Z"},
    {"reading":"2 Chronicles 27", "date":"2023-10-03T09:00:00.000Z"},
    {"reading":"2 Chronicles 28", "date":"2023-10-04T09:00:00.000Z"},
    {"reading":"2 Chronicles 29", "date":"2023-10-05T09:00:00.000Z"},
    {"reading":"2 Chronicles 30", "date":"2023-10-06T09:00:00.000Z"},
    {"reading":"2 Chronicles 31", "date":"2023-10-07T09:00:00.000Z"},
    {"reading":"2 Chronicles 32", "date":"2023-10-08T09:00:00.000Z"},
    {"reading":"2 Chronicles 33", "date":"2023-10-09T09:00:00.000Z"},
    {"reading":"2 Chronicles 34", "date":"2023-10-10T09:00:00.000Z"},
    {"reading":"2 Chronicles 35", "date":"2023-10-11T09:00:00.000Z"},
    {"reading":"2 Chronicles 36", "date":"2023-10-12T09:00:00.000Z"},
    {"reading":"Ezra 1", "date":"2023-10-13T09:00:00.000Z"},
    {"reading":"Ezra 2", "date":"2023-10-14T09:00:00.000Z"},
    {"reading":"Ezra 3", "date":"2023-10-15T09:00:00.000Z"},
    {"reading":"Ezra 4", "date":"2023-10-16T09:00:00.000Z"},
    {"reading":"Ezra 5", "date":"2023-10-17T09:00:00.000Z"},
    {"reading":"Ezra 6", "date":"2023-10-18T09:00:00.000Z"},
    {"reading":"Ezra 7", "date":"2023-10-19T09:00:00.000Z"},
    {"reading":"Ezra 8", "date":"2023-10-20T09:00:00.000Z"},
    {"reading":"Ezra 9", "date":"2023-10-21T09:00:00.000Z"},
    {"reading":"Ezra 10", "date":"2023-10-22T09:00:00.000Z"},
    {"reading":"Nehemiah 1", "date":"2023-10-23T09:00:00.000Z"},
    {"reading":"Nehemiah 2", "date":"2023-10-24T09:00:00.000Z"},
    {"reading":"Nehemiah 3", "date":"2023-10-25T09:00:00.000Z"},
    {"reading":"Nehemiah 4", "date":"2023-10-26T09:00:00.000Z"},
    {"reading":"Nehemiah 5", "date":"2023-10-27T09:00:00.000Z"},
    {"reading":"Nehemiah 6", "date":"2023-10-28T09:00:00.000Z"},
    {"reading":"Nehemiah 7", "date":"2023-10-29T09:00:00.000Z"},
    {"reading":"Nehemiah 8", "date":"2023-10-30T09:00:00.000Z"},
    {"reading":"Nehemiah 9", "date":"2023-10-31T09:00:00.000Z"},
    {"reading":"Nehemiah 10", "date":"2023-11-01T09:00:00.000Z"},
    {"reading":"Nehemiah 11", "date":"2023-11-02T09:00:00.000Z"},
    {"reading":"Nehemiah 12", "date":"2023-11-03T09:00:00.000Z"},
    {"reading":"Nehemiah 13", "date":"2023-11-04T09:00:00.000Z"},
    {"reading":"Esther 1", "date":"2023-11-05T09:00:00.000Z"},
    {"reading":"Esther 2", "date":"2023-11-06T09:00:00.000Z"},
    {"reading":"Esther 3", "date":"2023-11-07T09:00:00.000Z"},
    {"reading":"Esther 4", "date":"2023-11-08T09:00:00.000Z"},
    {"reading":"Esther 5", "date":"2023-11-09T09:00:00.000Z"},
    {"reading":"Esther 6", "date":"2023-11-10T09:00:00.000Z"},
    {"reading":"Esther 7", "date":"2023-11-11T09:00:00.000Z"},
    {"reading":"Esther 8", "date":"2023-11-12T09:00:00.000Z"},
    {"reading":"Esther 9", "date":"2023-11-13T09:00:00.000Z"},
    {"reading":"Esther 10", "date":"2023-11-14T09:00:00.000Z"},
    {"reading":"Job 1", "date":"2023-11-15T09:00:00.000Z"},
    {"reading":"Job 2", "date":"2023-11-16T09:00:00.000Z"},
    {"reading":"Job 3", "date":"2023-11-17T09:00:00.000Z"},
    {"reading":"Job 4", "date":"2023-11-18T09:00:00.000Z"},
    {"reading":"Job 5", "date":"2023-11-19T09:00:00.000Z"},
    {"reading":"Job 6", "date":"2023-11-20T09:00:00.000Z"},
    {"reading":"Job 7", "date":"2023-11-21T09:00:00.000Z"},
    {"reading":"Job 8", "date":"2023-11-22T09:00:00.000Z"},
    {"reading":"Job 9", "date":"2023-11-23T09:00:00.000Z"},
    {"reading":"Job 10", "date":"2023-11-24T09:00:00.000Z"},
    {"reading":"Job 11", "date":"2023-11-25T09:00:00.000Z"},
    {"reading":"Job 12", "date":"2023-11-26T09:00:00.000Z"},
    {"reading":"Job 13", "date":"2023-11-27T09:00:00.000Z"},
    {"reading":"Job 14", "date":"2023-11-28T09:00:00.000Z"},
    {"reading":"Job 15", "date":"2023-11-29T09:00:00.000Z"},
    {"reading":"Job 16", "date":"2023-11-30T09:00:00.000Z"},
    {"reading":"Job 17", "date":"2023-12-01T09:00:00.000Z"},
    {"reading":"Job 18", "date":"2023-12-02T09:00:00.000Z"},
    {"reading":"Job 19", "date":"2023-12-03T09:00:00.000Z"},
    {"reading":"Job 20", "date":"2023-12-04T09:00:00.000Z"},
    {"reading":"Job 21", "date":"2023-12-05T09:00:00.000Z"},
    {"reading":"Job 22", "date":"2023-12-06T09:00:00.000Z"},
    {"reading":"Job 23", "date":"2023-12-07T09:00:00.000Z"},
    {"reading":"Job 24", "date":"2023-12-08T09:00:00.000Z"},
    {"reading":"Job 25", "date":"2023-12-09T09:00:00.000Z"},
    {"reading":"Job 26", "date":"2023-12-10T09:00:00.000Z"},
    {"reading":"Job 27", "date":"2023-12-11T09:00:00.000Z"},
    {"reading":"Job 28", "date":"2023-12-12T09:00:00.000Z"},
    {"reading":"Job 29", "date":"2023-12-13T09:00:00.000Z"},
    {"reading":"Job 30", "date":"2023-12-14T09:00:00.000Z"},
    {"reading":"Job 31", "date":"2023-12-15T09:00:00.000Z"},
    {"reading":"Job 32", "date":"2023-12-16T09:00:00.000Z"},
    {"reading":"Job 33", "date":"2023-12-17T09:00:00.000Z"},
    {"reading":"Job 34", "date":"2023-12-18T09:00:00.000Z"},
    {"reading":"Job 35", "date":"2023-12-19T09:00:00.000Z"},
    {"reading":"Job 36", "date":"2023-12-20T09:00:00.000Z"},
    {"reading":"Job 37", "date":"2023-12-21T09:00:00.000Z"},
    {"reading":"Job 38", "date":"2023-12-22T09:00:00.000Z"},
    {"reading":"Job 39", "date":"2023-12-23T09:00:00.000Z"},
    {"reading":"Job 40", "date":"2023-12-24T09:00:00.000Z"},
    {"reading":"Job 41", "date":"2023-12-25T09:00:00.000Z"},
    {"reading":"Job 42", "date":"2023-12-26T09:00:00.000Z"},
    {"reading":"Psalm 1", "date":"2023-12-27T09:00:00.000Z"},
    {"reading":"Psalm 2", "date":"2023-12-28T09:00:00.000Z"},
    {"reading":"Psalm 3", "date":"2023-12-29T09:00:00.000Z"},
    {"reading":"Psalm 4", "date":"2023-12-30T09:00:00.000Z"},
    {"reading":"Psalm 5", "date":"2023-12-31T09:00:00.000Z"},
    {"reading":"Psalm 6", "date":"2024-01-01T09:00:00.000Z"},
    {"reading":"Psalm 7", "date":"2024-01-02T09:00:00.000Z"},
    {"reading":"Psalm 8", "date":"2024-01-03T09:00:00.000Z"},
    {"reading":"Psalm 9", "date":"2024-01-04T09:00:00.000Z"},
    {"reading":"Psalm 10", "date":"2024-01-05T09:00:00.000Z"},
    {"reading":"Psalm 11", "date":"2024-01-06T09:00:00.000Z"},
    {"reading":"Psalm 12", "date":"2024-01-07T09:00:00.000Z"},
    {"reading":"Psalm 13", "date":"2024-01-08T09:00:00.000Z"},
    {"reading":"Psalm 14", "date":"2024-01-09T09:00:00.000Z"},
    {"reading":"Psalm 15", "date":"2024-01-10T09:00:00.000Z"},
    {"reading":"Psalm 16", "date":"2024-01-11T09:00:00.000Z"},
    {"reading":"Psalm 17", "date":"2024-01-12T09:00:00.000Z"},
    {"reading":"Psalm 18", "date":"2024-01-13T09:00:00.000Z"},
    {"reading":"Psalm 19", "date":"2024-01-14T09:00:00.000Z"},
    {"reading":"Psalm 20", "date":"2024-01-15T09:00:00.000Z"},
    {"reading":"Psalm 21", "date":"2024-01-16T09:00:00.000Z"},
    {"reading":"Psalm 22", "date":"2024-01-17T09:00:00.000Z"},
    {"reading":"Psalm 23", "date":"2024-01-18T09:00:00.000Z"},
    {"reading":"Psalm 24", "date":"2024-01-19T09:00:00.000Z"},
    {"reading":"Psalm 25", "date":"2024-01-20T09:00:00.000Z"},
    {"reading":"Psalm 26", "date":"2024-01-21T09:00:00.000Z"},
    {"reading":"Psalm 27", "date":"2024-01-22T09:00:00.000Z"},
    {"reading":"Psalm 28", "date":"2024-01-23T09:00:00.000Z"},
    {"reading":"Psalm 29", "date":"2024-01-24T09:00:00.000Z"},
    {"reading":"Psalm 30", "date":"2024-01-25T09:00:00.000Z"},
    {"reading":"Psalm 31", "date":"2024-01-26T09:00:00.000Z"},
    {"reading":"Psalm 32", "date":"2024-01-27T09:00:00.000Z"},
    {"reading":"Psalm 33", "date":"2024-01-28T09:00:00.000Z"},
    {"reading":"Psalm 34", "date":"2024-01-29T09:00:00.000Z"},
    {"reading":"Psalm 35", "date":"2024-01-30T09:00:00.000Z"},
    {"reading":"Psalm 36", "date":"2024-01-31T09:00:00.000Z"},
    {"reading":"Psalm 37", "date":"2024-02-01T09:00:00.000Z"},
    {"reading":"Psalm 38", "date":"2024-02-02T09:00:00.000Z"},
    {"reading":"Psalm 39", "date":"2024-02-03T09:00:00.000Z"},
    {"reading":"Psalm 40", "date":"2024-02-04T09:00:00.000Z"},
    {"reading":"Psalm 41", "date":"2024-02-05T09:00:00.000Z"},
    {"reading":"Psalm 42", "date":"2024-02-06T09:00:00.000Z"},
    {"reading":"Psalm 43", "date":"2024-02-07T09:00:00.000Z"},
    {"reading":"Psalm 44", "date":"2024-02-08T09:00:00.000Z"},
    {"reading":"Psalm 45", "date":"2024-02-09T09:00:00.000Z"},
    {"reading":"Psalm 46", "date":"2024-02-10T09:00:00.000Z"},
    {"reading":"Psalm 47", "date":"2024-02-11T09:00:00.000Z"},
    {"reading":"Psalm 48", "date":"2024-02-12T09:00:00.000Z"},
    {"reading":"Psalm 49", "date":"2024-02-13T09:00:00.000Z"},
    {"reading":"Psalm 50", "date":"2024-02-14T09:00:00.000Z"},
    {"reading":"Psalm 51", "date":"2024-02-15T09:00:00.000Z"},
    {"reading":"Psalm 52", "date":"2024-02-16T09:00:00.000Z"},
    {"reading":"Psalm 53", "date":"2024-02-17T09:00:00.000Z"},
    {"reading":"Psalm 54", "date":"2024-02-18T09:00:00.000Z"},
    {"reading":"Psalm 55", "date":"2024-02-19T09:00:00.000Z"},
    {"reading":"Psalm 56", "date":"2024-02-20T09:00:00.000Z"},
    {"reading":"Psalm 57", "date":"2024-02-21T09:00:00.000Z"},
    {"reading":"Psalm 58", "date":"2024-02-22T09:00:00.000Z"},
    {"reading":"Psalm 59", "date":"2024-02-23T09:00:00.000Z"},
    {"reading":"Psalm 60", "date":"2024-02-24T09:00:00.000Z"},
    {"reading":"Psalm 61", "date":"2024-02-25T09:00:00.000Z"},
    {"reading":"Psalm 62", "date":"2024-02-26T09:00:00.000Z"},
    {"reading":"Psalm 63", "date":"2024-02-27T09:00:00.000Z"},
    {"reading":"Psalm 64", "date":"2024-02-28T09:00:00.000Z"},
    {"reading":"Psalm 65", "date":"2024-02-29T09:00:00.000Z"},
    {"reading":"Psalm 66", "date":"2024-03-01T09:00:00.000Z"},
    {"reading":"Psalm 67", "date":"2024-03-02T09:00:00.000Z"},
    {"reading":"Psalm 68", "date":"2024-03-03T09:00:00.000Z"},
    {"reading":"Psalm 69", "date":"2024-03-04T09:00:00.000Z"},
    {"reading":"Psalm 70", "date":"2024-03-05T09:00:00.000Z"},
    {"reading":"Psalm 71", "date":"2024-03-06T09:00:00.000Z"},
    {"reading":"Psalm 72", "date":"2024-03-07T09:00:00.000Z"},
    {"reading":"Psalm 73", "date":"2024-03-08T09:00:00.000Z"},
    {"reading":"Psalm 74", "date":"2024-03-09T09:00:00.000Z"},
    {"reading":"Psalm 75", "date":"2024-03-10T09:00:00.000Z"},
    {"reading":"Psalm 76", "date":"2024-03-11T09:00:00.000Z"},
    {"reading":"Psalm 77", "date":"2024-03-12T09:00:00.000Z"},
    {"reading":"Psalm 78", "date":"2024-03-13T09:00:00.000Z"},
    {"reading":"Psalm 79", "date":"2024-03-14T09:00:00.000Z"},
    {"reading":"Psalm 80", "date":"2024-03-15T09:00:00.000Z"},
    {"reading":"Psalm 81", "date":"2024-03-16T09:00:00.000Z"},
    {"reading":"Psalm 82", "date":"2024-03-17T09:00:00.000Z"},
    {"reading":"Psalm 83", "date":"2024-03-18T09:00:00.000Z"},
    {"reading":"Psalm 84", "date":"2024-03-19T09:00:00.000Z"},
    {"reading":"Psalm 85", "date":"2024-03-20T09:00:00.000Z"},
    {"reading":"Psalm 86", "date":"2024-03-21T09:00:00.000Z"},
    {"reading":"Psalm 87", "date":"2024-03-22T09:00:00.000Z"},
    {"reading":"Psalm 88", "date":"2024-03-23T09:00:00.000Z"},
    {"reading":"Psalm 89", "date":"2024-03-24T09:00:00.000Z"},
    {"reading":"Psalm 90", "date":"2024-03-25T09:00:00.000Z"},
    {"reading":"Psalm 91", "date":"2024-03-26T09:00:00.000Z"},
    {"reading":"Psalm 92", "date":"2024-03-27T09:00:00.000Z"},
    {"reading":"Psalm 93", "date":"2024-03-28T09:00:00.000Z"},
    {"reading":"Psalm 94", "date":"2024-03-29T09:00:00.000Z"},
    {"reading":"Psalm 95", "date":"2024-03-30T09:00:00.000Z"},
    {"reading":"Psalm 96", "date":"2024-03-31T09:00:00.000Z"},
    {"reading":"Psalm 97", "date":"2024-04-01T09:00:00.000Z"},
    {"reading":"Psalm 98", "date":"2024-04-02T09:00:00.000Z"},
    {"reading":"Psalm 99", "date":"2024-04-03T09:00:00.000Z"},
    {"reading":"Psalm 100", "date":"2024-04-04T09:00:00.000Z"},
    {"reading":"Psalm 101", "date":"2024-04-05T09:00:00.000Z"},
    {"reading":"Psalm 102", "date":"2024-04-06T09:00:00.000Z"},
    {"reading":"Psalm 103", "date":"2024-04-07T09:00:00.000Z"},
    {"reading":"Psalm 104", "date":"2024-04-08T09:00:00.000Z"},
    {"reading":"Psalm 105", "date":"2024-04-09T09:00:00.000Z"},
    {"reading":"Psalm 106", "date":"2024-04-10T09:00:00.000Z"},
    {"reading":"Psalm 107", "date":"2024-04-11T09:00:00.000Z"},
    {"reading":"Psalm 108", "date":"2024-04-12T09:00:00.000Z"},
    {"reading":"Psalm 109", "date":"2024-04-13T09:00:00.000Z"},
    {"reading":"Psalm 110", "date":"2024-04-14T09:00:00.000Z"},
    {"reading":"Psalm 111", "date":"2024-04-15T09:00:00.000Z"},
    {"reading":"Psalm 112", "date":"2024-04-16T09:00:00.000Z"},
    {"reading":"Psalm 113", "date":"2024-04-17T09:00:00.000Z"},
    {"reading":"Psalm 114", "date":"2024-04-18T09:00:00.000Z"},
    {"reading":"Psalm 115", "date":"2024-04-19T09:00:00.000Z"},
    {"reading":"Psalm 116", "date":"2024-04-20T09:00:00.000Z"},
    {"reading":"Psalm 117", "date":"2024-04-21T09:00:00.000Z"},
    {"reading":"Psalm 118", "date":"2024-04-22T09:00:00.000Z"},
    {"reading":"Psalm 119", "date":"2024-04-23T09:00:00.000Z"},
    {"reading":"Psalm 120", "date":"2024-04-24T09:00:00.000Z"},
    {"reading":"Psalm 121", "date":"2024-04-25T09:00:00.000Z"},
    {"reading":"Psalm 122", "date":"2024-04-26T09:00:00.000Z"},
    {"reading":"Psalm 123", "date":"2024-04-27T09:00:00.000Z"},
    {"reading":"Psalm 124", "date":"2024-04-28T09:00:00.000Z"},
    {"reading":"Psalm 125", "date":"2024-04-29T09:00:00.000Z"},
    {"reading":"Psalm 126", "date":"2024-04-30T09:00:00.000Z"},
    {"reading":"Psalm 127", "date":"2024-05-01T09:00:00.000Z"},
    {"reading":"Psalm 128", "date":"2024-05-02T09:00:00.000Z"},
    {"reading":"Psalm 129", "date":"2024-05-03T09:00:00.000Z"},
    {"reading":"Psalm 130", "date":"2024-05-04T09:00:00.000Z"},
    {"reading":"Psalm 131", "date":"2024-05-05T09:00:00.000Z"},
    {"reading":"Psalm 132", "date":"2024-05-06T09:00:00.000Z"},
    {"reading":"Psalm 133", "date":"2024-05-07T09:00:00.000Z"},
    {"reading":"Psalm 134", "date":"2024-05-08T09:00:00.000Z"},
    {"reading":"Psalm 135", "date":"2024-05-09T09:00:00.000Z"},
    {"reading":"Psalm 136", "date":"2024-05-10T09:00:00.000Z"},
    {"reading":"Psalm 137", "date":"2024-05-11T09:00:00.000Z"},
    {"reading":"Psalm 138", "date":"2024-05-12T09:00:00.000Z"},
    {"reading":"Psalm 139", "date":"2024-05-13T09:00:00.000Z"},
    {"reading":"Psalm 140", "date":"2024-05-14T09:00:00.000Z"},
    {"reading":"Psalm 141", "date":"2024-05-15T09:00:00.000Z"},
    {"reading":"Psalm 142", "date":"2024-05-16T09:00:00.000Z"},
    {"reading":"Psalm 143", "date":"2024-05-17T09:00:00.000Z"},
    {"reading":"Psalm 144", "date":"2024-05-18T09:00:00.000Z"},
    {"reading":"Psalm 145", "date":"2024-05-19T09:00:00.000Z"},
    {"reading":"Psalm 146", "date":"2024-05-20T09:00:00.000Z"},
    {"reading":"Psalm 147", "date":"2024-05-21T09:00:00.000Z"},
    {"reading":"Psalm 148", "date":"2024-05-22T09:00:00.000Z"},
    {"reading":"Psalm 149", "date":"2024-05-23T09:00:00.000Z"},
    {"reading":"Psalm 150", "date":"2024-05-24T09:00:00.000Z"},
    {"reading":"Proverbs 1", "date":"2024-05-25T09:00:00.000Z"},
    {"reading":"Proverbs 2", "date":"2024-05-26T09:00:00.000Z"},
    {"reading":"Proverbs 3", "date":"2024-05-27T09:00:00.000Z"},
    {"reading":"Proverbs 4", "date":"2024-05-28T09:00:00.000Z"},
    {"reading":"Proverbs 5", "date":"2024-05-29T09:00:00.000Z"},
    {"reading":"Proverbs 6", "date":"2024-05-30T09:00:00.000Z"},
    {"reading":"Proverbs 7", "date":"2024-05-31T09:00:00.000Z"},
    {"reading":"Proverbs 8", "date":"2024-06-01T09:00:00.000Z"},
    {"reading":"Proverbs 9", "date":"2024-06-02T09:00:00.000Z"},
    {"reading":"Proverbs 10", "date":"2024-06-03T09:00:00.000Z"},
    {"reading":"Proverbs 11", "date":"2024-06-04T09:00:00.000Z"},
    {"reading":"Proverbs 12", "date":"2024-06-05T09:00:00.000Z"},
    {"reading":"Proverbs 13", "date":"2024-06-06T09:00:00.000Z"},
    {"reading":"Proverbs 14", "date":"2024-06-07T09:00:00.000Z"},
    {"reading":"Proverbs 15", "date":"2024-06-08T09:00:00.000Z"},
    {"reading":"Proverbs 16", "date":"2024-06-09T09:00:00.000Z"},
    {"reading":"Proverbs 17", "date":"2024-06-10T09:00:00.000Z"},
    {"reading":"Proverbs 18", "date":"2024-06-11T09:00:00.000Z"},
    {"reading":"Proverbs 19", "date":"2024-06-12T09:00:00.000Z"},
    {"reading":"Proverbs 20", "date":"2024-06-13T09:00:00.000Z"},
    {"reading":"Proverbs 21", "date":"2024-06-14T09:00:00.000Z"},
    {"reading":"Proverbs 22", "date":"2024-06-15T09:00:00.000Z"},
    {"reading":"Proverbs 23", "date":"2024-06-16T09:00:00.000Z"},
    {"reading":"Luke 17", "date":"2024-06-17T09:00:00.000Z"},
    {"reading":"Luke 18", "date":"2024-06-18T09:00:00.000Z"},
    {"reading":"Luke 19", "date":"2024-06-19T09:00:00.000Z"},
    {"reading":"Luke 20", "date":"2024-06-20T09:00:00.000Z"},
    {"reading":"Luke 21", "date":"2024-06-21T09:00:00.000Z"},
    {"reading":"Luke 22", "date":"2024-06-22T09:00:00.000Z"},
    {"reading":"Luke 23", "date":"2024-06-23T09:00:00.000Z"},
    {"reading":"Luke 24", "date":"2024-06-24T09:00:00.000Z"},
    {"reading":"John 1", "date":"2024-06-25T09:00:00.000Z"},
    {"reading":"John 2", "date":"2024-06-26T09:00:00.000Z"},
    {"reading":"John 3", "date":"2024-06-27T09:00:00.000Z"},
    {"reading":"John 4", "date":"2024-06-28T09:00:00.000Z"},
    {"reading":"John 5", "date":"2024-06-29T09:00:00.000Z"},
    {"reading":"John 6", "date":"2024-06-30T09:00:00.000Z"},
    {"reading":"John 7", "date":"2024-07-01T09:00:00.000Z"},
    {"reading":"John 8", "date":"2024-07-02T09:00:00.000Z"},
    {"reading":"John 9", "date":"2024-07-03T09:00:00.000Z"},
    {"reading":"John 10", "date":"2024-07-04T09:00:00.000Z"},
    {"reading":"John 11", "date":"2024-07-05T09:00:00.000Z"},
    {"reading":"John 12", "date":"2024-07-06T09:00:00.000Z"},
    {"reading":"John 13", "date":"2024-07-07T09:00:00.000Z"},
    {"reading":"John 14", "date":"2024-07-08T09:00:00.000Z"},
    {"reading":"John 15", "date":"2024-07-09T09:00:00.000Z"},
    {"reading":"John 16", "date":"2024-07-10T09:00:00.000Z"},
    {"reading":"John 17", "date":"2024-07-11T09:00:00.000Z"},
    {"reading":"John 18", "date":"2024-07-12T09:00:00.000Z"},
    {"reading":"John 19", "date":"2024-07-13T09:00:00.000Z"},
    {"reading":"John 20", "date":"2024-07-14T09:00:00.000Z"},
    {"reading":"John 21", "date":"2024-07-15T09:00:00.000Z"},
    {"reading":"Acts 1", "date":"2024-07-16T09:00:00.000Z"},
    {"reading":"Acts 2", "date":"2024-07-17T09:00:00.000Z"},
    {"reading":"Acts 3", "date":"2024-07-18T09:00:00.000Z"},
    {"reading":"Acts 4", "date":"2024-07-19T09:00:00.000Z"},
    {"reading":"Acts 5", "date":"2024-07-20T09:00:00.000Z"},
    {"reading":"Acts 6", "date":"2024-07-21T09:00:00.000Z"},
    {"reading":"Acts 7", "date":"2024-07-22T09:00:00.000Z"},
    {"reading":"Acts 8", "date":"2024-07-23T09:00:00.000Z"},
    {"reading":"Acts 9", "date":"2024-07-24T09:00:00.000Z"},
    {"reading":"Acts 10", "date":"2024-07-25T09:00:00.000Z"},
    {"reading":"Acts 11", "date":"2024-07-26T09:00:00.000Z"},
    {"reading":"Acts 12", "date":"2024-07-27T09:00:00.000Z"},
    {"reading":"Acts 13", "date":"2024-07-28T09:00:00.000Z"},
    {"reading":"Acts 14", "date":"2024-07-29T09:00:00.000Z"},
    {"reading":"Acts 15", "date":"2024-07-30T09:00:00.000Z"},
    {"reading":"Acts 16", "date":"2024-07-31T09:00:00.000Z"},
    {"reading":"Acts 17", "date":"2024-08-01T09:00:00.000Z"},
    {"reading":"Acts 18", "date":"2024-08-02T09:00:00.000Z"},
    {"reading":"Acts 19", "date":"2024-08-03T09:00:00.000Z"},
    {"reading":"Acts 20", "date":"2024-08-04T09:00:00.000Z"},
    {"reading":"Acts 21", "date":"2024-08-05T09:00:00.000Z"},
    {"reading":"Acts 22", "date":"2024-08-06T09:00:00.000Z"},
    {"reading":"Acts 23", "date":"2024-08-07T09:00:00.000Z"},
    {"reading":"Acts 24", "date":"2024-08-08T09:00:00.000Z"},
    {"reading":"Acts 25", "date":"2024-08-09T09:00:00.000Z"},
    {"reading":"Acts 26", "date":"2024-08-10T09:00:00.000Z"},
    {"reading":"Acts 27", "date":"2024-08-11T09:00:00.000Z"},
    {"reading":"Acts 28", "date":"2024-08-12T09:00:00.000Z"},
    {"reading":"Romans 1", "date":"2024-08-13T09:00:00.000Z"},
    {"reading":"Romans 2", "date":"2024-08-14T09:00:00.000Z"},
    {"reading":"Romans 3", "date":"2024-08-15T09:00:00.000Z"},
    {"reading":"Romans 4", "date":"2024-08-16T09:00:00.000Z"},
    {"reading":"Romans 5", "date":"2024-08-17T09:00:00.000Z"},
    {"reading":"Romans 6", "date":"2024-08-18T09:00:00.000Z"},
    {"reading":"Romans 7", "date":"2024-08-19T09:00:00.000Z"},
    {"reading":"Romans 8", "date":"2024-08-20T09:00:00.000Z"},
    {"reading":"Romans 9", "date":"2024-08-21T09:00:00.000Z"},
    {"reading":"Romans 10", "date":"2024-08-22T09:00:00.000Z"},
    {"reading":"Romans 11", "date":"2024-08-23T09:00:00.000Z"},
    {"reading":"Romans 12", "date":"2024-08-24T09:00:00.000Z"},
    {"reading":"Romans 13", "date":"2024-08-25T09:00:00.000Z"},
    {"reading":"Romans 14", "date":"2024-08-26T09:00:00.000Z"},
    {"reading":"Romans 15", "date":"2024-08-27T09:00:00.000Z"},
    {"reading":"Romans 16", "date":"2024-08-28T09:00:00.000Z"},
    {"reading":"Isaiah 46", "date":"2024-08-29T09:00:00.000Z"},
    {"reading":"Isaiah 47", "date":"2024-08-30T09:00:00.000Z"},
    {"reading":"Isaiah 48", "date":"2024-08-31T09:00:00.000Z"},
    {"reading":"Isaiah 49", "date":"2024-09-01T09:00:00.000Z"},
    {"reading":"Isaiah 50", "date":"2024-09-02T09:00:00.000Z"},
    {"reading":"Isaiah 51", "date":"2024-09-03T09:00:00.000Z"},
    {"reading":"Isaiah 52", "date":"2024-09-04T09:00:00.000Z"},
    {"reading":"Isaiah 53", "date":"2024-09-05T09:00:00.000Z"},
    {"reading":"Isaiah 54", "date":"2024-09-06T09:00:00.000Z"},
    {"reading":"Isaiah 55", "date":"2024-09-07T09:00:00.000Z"},
    {"reading":"Isaiah 56", "date":"2024-09-08T09:00:00.000Z"},
    {"reading":"Isaiah 57", "date":"2024-09-09T09:00:00.000Z"},
    {"reading":"Isaiah 58", "date":"2024-09-10T09:00:00.000Z"},
    {"reading":"Isaiah 59", "date":"2024-09-11T09:00:00.000Z"},
    {"reading":"Isaiah 60", "date":"2024-09-12T09:00:00.000Z"},
    {"reading":"Isaiah 61", "date":"2024-09-13T09:00:00.000Z"},
    {"reading":"Isaiah 62", "date":"2024-09-14T09:00:00.000Z"},
    {"reading":"Isaiah 63", "date":"2024-09-15T09:00:00.000Z"},
    {"reading":"Isaiah 64", "date":"2024-09-16T09:00:00.000Z"},
    {"reading":"Isaiah 65", "date":"2024-09-17T09:00:00.000Z"},
    {"reading":"Isaiah 66", "date":"2024-09-18T09:00:00.000Z"},
    {"reading":"Jeremiah 1", "date":"2024-09-19T09:00:00.000Z"},
    {"reading":"Jeremiah 2", "date":"2024-09-20T09:00:00.000Z"},
    {"reading":"Jeremiah 3", "date":"2024-09-21T09:00:00.000Z"},
    {"reading":"Jeremiah 4", "date":"2024-09-22T09:00:00.000Z"},
    {"reading":"Jeremiah 5", "date":"2024-09-23T09:00:00.000Z"},
    {"reading":"Jeremiah 6", "date":"2024-09-24T09:00:00.000Z"},
    {"reading":"Jeremiah 7", "date":"2024-09-25T09:00:00.000Z"},
    {"reading":"Jeremiah 8", "date":"2024-09-26T09:00:00.000Z"},
    {"reading":"Jeremiah 9", "date":"2024-09-27T09:00:00.000Z"},
    {"reading":"Jeremiah 10", "date":"2024-09-28T09:00:00.000Z"},
    {"reading":"Jeremiah 11", "date":"2024-09-29T09:00:00.000Z"},
    {"reading":"Jeremiah 12", "date":"2024-09-30T09:00:00.000Z"},
    {"reading":"Jeremiah 13", "date":"2024-10-01T09:00:00.000Z"},
    {"reading":"Jeremiah 14", "date":"2024-10-02T09:00:00.000Z"},
    {"reading":"Jeremiah 15", "date":"2024-10-03T09:00:00.000Z"},
    {"reading":"Jeremiah 16", "date":"2024-10-04T09:00:00.000Z"},
    {"reading":"Jeremiah 17", "date":"2024-10-05T09:00:00.000Z"},
    {"reading":"Jeremiah 18", "date":"2024-10-06T09:00:00.000Z"},
    {"reading":"Jeremiah 19", "date":"2024-10-07T09:00:00.000Z"},
    {"reading":"Jeremiah 20", "date":"2024-10-08T09:00:00.000Z"},
    {"reading":"Jeremiah 21", "date":"2024-10-09T09:00:00.000Z"},
    {"reading":"Jeremiah 22", "date":"2024-10-10T09:00:00.000Z"},
    {"reading":"Jeremiah 23", "date":"2024-10-11T09:00:00.000Z"},
    {"reading":"Jeremiah 24", "date":"2024-10-12T09:00:00.000Z"},
    {"reading":"Jeremiah 25", "date":"2024-10-13T09:00:00.000Z"},
    {"reading":"Jeremiah 26", "date":"2024-10-14T09:00:00.000Z"},
    {"reading":"Jeremiah 27", "date":"2024-10-15T09:00:00.000Z"},
    {"reading":"Jeremiah 28", "date":"2024-10-16T09:00:00.000Z"},
    {"reading":"Jeremiah 29", "date":"2024-10-17T09:00:00.000Z"},
    {"reading":"Jeremiah 30", "date":"2024-10-18T09:00:00.000Z"},
    {"reading":"Jeremiah 31", "date":"2024-10-19T09:00:00.000Z"},
    {"reading":"Jeremiah 32", "date":"2024-10-20T09:00:00.000Z"},
    {"reading":"Jeremiah 33", "date":"2024-10-21T09:00:00.000Z"},
    {"reading":"Jeremiah 34", "date":"2024-10-22T09:00:00.000Z"},
    {"reading":"Jeremiah 35", "date":"2024-10-23T09:00:00.000Z"},
    {"reading":"Jeremiah 36", "date":"2024-10-24T09:00:00.000Z"},
    {"reading":"Jeremiah 37", "date":"2024-10-25T09:00:00.000Z"},
    {"reading":"Jeremiah 38", "date":"2024-10-26T09:00:00.000Z"},
    {"reading":"Jeremiah 39", "date":"2024-10-27T09:00:00.000Z"},
    {"reading":"Jeremiah 40", "date":"2024-10-28T09:00:00.000Z"},
    {"reading":"Jeremiah 41", "date":"2024-10-29T09:00:00.000Z"},
    {"reading":"Jeremiah 42", "date":"2024-10-30T09:00:00.000Z"},
    {"reading":"Jeremiah 43", "date":"2024-10-31T09:00:00.000Z"},
    {"reading":"Jeremiah 44", "date":"2024-11-01T09:00:00.000Z"},
    {"reading":"Jeremiah 45", "date":"2024-11-02T09:00:00.000Z"},
    {"reading":"Jeremiah 46", "date":"2024-11-03T09:00:00.000Z"},
    {"reading":"Jeremiah 47", "date":"2024-11-04T09:00:00.000Z"},
    {"reading":"Jeremiah 48", "date":"2024-11-05T09:00:00.000Z"},
    {"reading":"Jeremiah 49", "date":"2024-11-06T09:00:00.000Z"},
    {"reading":"Jeremiah 50", "date":"2024-11-07T09:00:00.000Z"},
    {"reading":"Jeremiah 51", "date":"2024-11-08T09:00:00.000Z"},
    {"reading":"Jeremiah 52", "date":"2024-11-09T09:00:00.000Z"},
    {"reading":"Lamentations 1", "date":"2024-11-10T09:00:00.000Z"},
    {"reading":"Lamentations 2", "date":"2024-11-11T09:00:00.000Z"},
    {"reading":"Lamentations 3", "date":"2024-11-12T09:00:00.000Z"},
    {"reading":"Lamentations 4", "date":"2024-11-13T09:00:00.000Z"},
    {"reading":"Lamentations 5", "date":"2024-11-14T09:00:00.000Z"},
    {"reading":"Ezekiel 1", "date":"2024-11-15T09:00:00.000Z"},
    {"reading":"Ezekiel 2", "date":"2024-11-16T09:00:00.000Z"},
    {"reading":"Ezekiel 3", "date":"2024-11-17T09:00:00.000Z"},
    {"reading":"Ezekiel 4", "date":"2024-11-18T09:00:00.000Z"},
    {"reading":"Ezekiel 5", "date":"2024-11-19T09:00:00.000Z"},
    {"reading":"Ezekiel 6", "date":"2024-11-20T09:00:00.000Z"},
    {"reading":"Ezekiel 7", "date":"2024-11-21T09:00:00.000Z"},
    {"reading":"Ezekiel 8", "date":"2024-11-22T09:00:00.000Z"},
    {"reading":"Ezekiel 9", "date":"2024-11-23T09:00:00.000Z"},
    {"reading":"Ezekiel 10", "date":"2024-11-24T09:00:00.000Z"},
    {"reading":"Ezekiel 11", "date":"2024-11-25T09:00:00.000Z"},
    {"reading":"Ezekiel 12", "date":"2024-11-26T09:00:00.000Z"},
    {"reading":"Ezekiel 13", "date":"2024-11-27T09:00:00.000Z"},
    {"reading":"Ezekiel 14", "date":"2024-11-28T09:00:00.000Z"},
    {"reading":"Ezekiel 15", "date":"2024-11-29T09:00:00.000Z"},
    {"reading":"Ezekiel 16", "date":"2024-11-30T09:00:00.000Z"},
    {"reading":"Ezekiel 17", "date":"2024-12-01T09:00:00.000Z"},
    {"reading":"Ezekiel 18", "date":"2024-12-02T09:00:00.000Z"},
    {"reading":"Ezekiel 19", "date":"2024-12-03T09:00:00.000Z"},
    {"reading":"Ezekiel 20", "date":"2024-12-04T09:00:00.000Z"},
    {"reading":"Ezekiel 21", "date":"2024-12-05T09:00:00.000Z"},
    {"reading":"Ezekiel 22", "date":"2024-12-06T09:00:00.000Z"},
    {"reading":"Ezekiel 23", "date":"2024-12-07T09:00:00.000Z"},
    {"reading":"Ezekiel 24", "date":"2024-12-08T09:00:00.000Z"},
    {"reading":"Ezekiel 25", "date":"2024-12-09T09:00:00.000Z"},
    {"reading":"Ezekiel 26", "date":"2024-12-10T09:00:00.000Z"},
    {"reading":"Ezekiel 27", "date":"2024-12-11T09:00:00.000Z"},
    {"reading":"Ezekiel 28", "date":"2024-12-12T09:00:00.000Z"},
    {"reading":"Ezekiel 29", "date":"2024-12-13T09:00:00.000Z"},
    {"reading":"Ezekiel 30", "date":"2024-12-14T09:00:00.000Z"},
    {"reading":"Ezekiel 31", "date":"2024-12-15T09:00:00.000Z"},
    {"reading":"Ezekiel 32", "date":"2024-12-16T09:00:00.000Z"},
    {"reading":"Ezekiel 33", "date":"2024-12-17T09:00:00.000Z"},
    {"reading":"Ezekiel 34", "date":"2024-12-18T09:00:00.000Z"},
    {"reading":"Ezekiel 35", "date":"2024-12-19T09:00:00.000Z"},
    {"reading":"Ezekiel 36", "date":"2024-12-20T09:00:00.000Z"},
    {"reading":"Ezekiel 37", "date":"2024-12-21T09:00:00.000Z"},
    {"reading":"Ezekiel 38", "date":"2024-12-22T09:00:00.000Z"},
    {"reading":"Ezekiel 39", "date":"2024-12-23T09:00:00.000Z"},
    {"reading":"Ezekiel 40", "date":"2024-12-24T09:00:00.000Z"},
    {"reading":"Ezekiel 41", "date":"2024-12-25T09:00:00.000Z"},
    {"reading":"Ezekiel 42", "date":"2024-12-26T09:00:00.000Z"},
    {"reading":"Ezekiel 43", "date":"2024-12-27T09:00:00.000Z"},
    {"reading":"Ezekiel 44", "date":"2024-12-28T09:00:00.000Z"},
    {"reading":"Ezekiel 45", "date":"2024-12-29T09:00:00.000Z"},
    {"reading":"Ezekiel 46", "date":"2024-12-30T09:00:00.000Z"},
    {"reading":"Ezekiel 47", "date":"2024-12-31T09:00:00.000Z"},
    {"reading":"Ezekiel 48", "date":"2025-01-01T09:00:00.000Z"},
    {"reading":"Daniel 1", "date":"2025-01-02T09:00:00.000Z"},
    {"reading":"Daniel 2", "date":"2025-01-03T09:00:00.000Z"},
    {"reading":"Daniel 3", "date":"2025-01-04T09:00:00.000Z"},
    {"reading":"Daniel 4", "date":"2025-01-05T09:00:00.000Z"},
    {"reading":"Daniel 5", "date":"2025-01-06T09:00:00.000Z"},
    {"reading":"Daniel 6", "date":"2025-01-07T09:00:00.000Z"},
    {"reading":"Daniel 7", "date":"2025-01-08T09:00:00.000Z"},
    {"reading":"Daniel 8", "date":"2025-01-09T09:00:00.000Z"},
    {"reading":"Daniel 9", "date":"2025-01-10T09:00:00.000Z"},
    {"reading":"Daniel 10", "date":"2025-01-11T09:00:00.000Z"},
    {"reading":"Daniel 11", "date":"2025-01-12T09:00:00.000Z"},
    {"reading":"Daniel 12", "date":"2025-01-13T09:00:00.000Z"},
    {"reading":"Hosea 1", "date":"2025-01-14T09:00:00.000Z"},
    {"reading":"Hosea 2", "date":"2025-01-15T09:00:00.000Z"},
    {"reading":"Hosea 3", "date":"2025-01-16T09:00:00.000Z"},
    {"reading":"Hosea 4", "date":"2025-01-17T09:00:00.000Z"},
    {"reading":"Hosea 5", "date":"2025-01-18T09:00:00.000Z"},
    {"reading":"Hosea 6", "date":"2025-01-19T09:00:00.000Z"},
    {"reading":"Hosea 7", "date":"2025-01-20T09:00:00.000Z"},
    {"reading":"Hosea 8", "date":"2025-01-21T09:00:00.000Z"},
    {"reading":"Hosea 9", "date":"2025-01-22T09:00:00.000Z"},
    {"reading":"Hosea 10", "date":"2025-01-23T09:00:00.000Z"},
    {"reading":"Hosea 11", "date":"2025-01-24T09:00:00.000Z"},
    {"reading":"Hosea 12", "date":"2025-01-25T09:00:00.000Z"},
    {"reading":"Hosea 13", "date":"2025-01-26T09:00:00.000Z"},
    {"reading":"Hosea 14", "date":"2025-01-27T09:00:00.000Z"},
    {"reading":"Joel 1", "date":"2025-01-28T09:00:00.000Z"},
    {"reading":"Joel 2", "date":"2025-01-29T09:00:00.000Z"},
    {"reading":"Joel 3", "date":"2025-01-30T09:00:00.000Z"},
    {"reading":"Amos 1", "date":"2025-01-31T09:00:00.000Z"},
    {"reading":"Amos 2", "date":"2025-02-01T09:00:00.000Z"},
    {"reading":"Amos 3", "date":"2025-02-02T09:00:00.000Z"},
    {"reading":"Amos 4", "date":"2025-02-03T09:00:00.000Z"},
    {"reading":"Amos 5", "date":"2025-02-04T09:00:00.000Z"},
    {"reading":"Amos 6", "date":"2025-02-05T09:00:00.000Z"},
    {"reading":"Amos 7", "date":"2025-02-06T09:00:00.000Z"},
    {"reading":"Amos 8", "date":"2025-02-07T09:00:00.000Z"},
    {"reading":"Amos 9", "date":"2025-02-08T09:00:00.000Z"},
    {"reading":"Obadiah", "date":"2025-02-09T09:00:00.000Z"},
    {"reading":"Jonah 1", "date":"2025-02-10T09:00:00.000Z"},
    {"reading":"Jonah 2", "date":"2025-02-11T09:00:00.000Z"},
    {"reading":"Jonah 3", "date":"2025-02-12T09:00:00.000Z"},
    {"reading":"Jonah 4", "date":"2025-02-13T09:00:00.000Z"},
    {"reading":"Micah 1", "date":"2025-02-14T09:00:00.000Z"},
    {"reading":"Micah 2", "date":"2025-02-15T09:00:00.000Z"},
    {"reading":"Micah 3", "date":"2025-02-16T09:00:00.000Z"},
    {"reading":"Micah 4", "date":"2025-02-17T09:00:00.000Z"},
    {"reading":"Micah 5", "date":"2025-02-18T09:00:00.000Z"},
    {"reading":"Micah 6", "date":"2025-02-19T09:00:00.000Z"},
    {"reading":"Micah 7", "date":"2025-02-20T09:00:00.000Z"},
    {"reading":"Nahum 1", "date":"2025-02-21T09:00:00.000Z"},
    {"reading":"Nahum 2", "date":"2025-02-22T09:00:00.000Z"},
    {"reading":"Nahum 3", "date":"2025-02-23T09:00:00.000Z"},
    {"reading":"Habakkuk 1", "date":"2025-02-24T09:00:00.000Z"},
    {"reading":"Habakkuk 2", "date":"2025-02-25T09:00:00.000Z"},
    {"reading":"Habakkuk 3", "date":"2025-02-26T09:00:00.000Z"},
    {"reading":"Zephaniah 1", "date":"2025-02-27T09:00:00.000Z"},
    {"reading":"Zephaniah 2", "date":"2025-02-28T09:00:00.000Z"},
    {"reading":"Zephaniah 3", "date":"2025-03-01T09:00:00.000Z"},
    {"reading":"Haggai 1", "date":"2025-03-02T09:00:00.000Z"},
    {"reading":"Haggai 2", "date":"2025-03-03T09:00:00.000Z"},
    {"reading":"Zechariah 1", "date":"2025-03-04T09:00:00.000Z"},
    {"reading":"Zechariah 2", "date":"2025-03-05T09:00:00.000Z"},
    {"reading":"Zechariah 3", "date":"2025-03-06T09:00:00.000Z"},
    {"reading":"Zechariah 4", "date":"2025-03-07T09:00:00.000Z"},
    {"reading":"Zechariah 5", "date":"2025-03-08T09:00:00.000Z"},
    {"reading":"Zechariah 6", "date":"2025-03-09T09:00:00.000Z"},
    {"reading":"Zechariah 7", "date":"2025-03-10T09:00:00.000Z"},
    {"reading":"Zechariah 8", "date":"2025-03-11T09:00:00.000Z"},
    {"reading":"Zechariah 9", "date":"2025-03-12T09:00:00.000Z"},
    {"reading":"Zechariah 10", "date":"2025-03-13T09:00:00.000Z"},
    {"reading":"Zechariah 11", "date":"2025-03-14T09:00:00.000Z"},
    {"reading":"Zechariah 12", "date":"2025-03-15T09:00:00.000Z"},
    {"reading":"Zechariah 13", "date":"2025-03-16T09:00:00.000Z"},
    {"reading":"Zechariah 14", "date":"2025-03-17T09:00:00.000Z"},
    {"reading":"Malachi 1", "date":"2025-03-18T09:00:00.000Z"},
    {"reading":"Malachi 2", "date":"2025-03-19T09:00:00.000Z"},
    {"reading":"Malachi 3", "date":"2025-03-20T09:00:00.000Z"},
    {"reading":"Malachi 4", "date":"2025-03-21T09:00:00.000Z"}
]
